preservationdatabase/__init__.py
preservationdatabase/cli.py
preservationdatabase/constants.py
preservationdatabase/environment.py
preservationdatabase/example_settings.py
preservationdatabase/exporter.py
preservationdatabase/models.py
preservationdatabase/urls.py
preservationdatabase/utils.py
preservationdatabase/test_data/tests.jsonl
preservationdatabase/tests/__init__.py
preservationdatabase/tests/test_archives.py
preservation_database-0.0.106.dist-info/METADATA
preservation_database-0.0.106.dist-info/WHEEL
preservation_database-0.0.106.dist-info/top_level.txt
preservation_database-0.0.106.dist-info/RECORD
