Metadata-Version: 2.1
Name: preservation-database
Version: 0.0.106
Summary: A database builder for digital preservation information.
Home-page: https://gitlab.com/crossref/labs/preservationDatabase
Author: Martin Paul Eve
Author-email: meve@crossref.org
Maintainer-email: Martin Paul Eve <meve@crossref.org>
Project-URL: homepage, https://labs.crossref.org
Project-URL: documentation, https://labs.crossref.org
Project-URL: repository, https://gitlab.com/crossref/labs/preservationDatabase
Project-URL: changelog, https://gitlab.com/crossref/labs/preservation-data/-/blob/main/CHANGELOG.md
Keywords: digital preservation,academic
Classifier: Development Status :: 4 - Beta
Classifier: Programming Language :: Python
Requires-Python: >=3.8
Requires-Dist: Django >=4.0
Requires-Dist: rich
Requires-Dist: django
Requires-Dist: click
Requires-Dist: requests
Requires-Dist: crossrefapi
Requires-Dist: django-macros
Requires-Dist: gunicorn
Requires-Dist: djangorestframework
Requires-Dist: markdown
Requires-Dist: django-filter
Requires-Dist: apache-airflow
Requires-Dist: boto3
Requires-Dist: pytz
Requires-Dist: msgspec
Requires-Dist: humanfriendly
Requires-Dist: psycopg2-binary
Requires-Dist: lxml
Requires-Dist: joblib
Requires-Dist: case-converter
